{
  "updated": "2026-03-10",
  "water_year": 2026,
  "basin": {
    "swe_change_24h": 0.44,
    "days_since_snow": 0,
    "melt_alert": false,
    "density_pct": 392.4
  },
  "stations": [
    {
      "id": "679:WA:SNTL",
      "name": "Paradise",
      "elevation": 5150,
      "swe_in": 27.1,
      "depth_in": 76.0,
      "temp_f": 17.6,
      "swe_change_24h": 0.6,
      "days_since_snow": 0,
      "melt_alert": false,
      "density_pct": 427.9
    },
    {
      "id": "642:WA:SNTL",
      "name": "Morse Lake",
      "elevation": 5400,
      "swe_in": 27.0,
      "depth_in": 75.0,
      "temp_f": 15.4,
      "swe_change_24h": 0.4,
      "days_since_snow": 0,
      "melt_alert": false,
      "density_pct": 432.0
    },
    {
      "id": "672:WA:SNTL",
      "name": "Olallie Meadows",
      "elevation": 4010,
      "swe_in": 16.3,
      "depth_in": 41.0,
      "temp_f": 22.6,
      "swe_change_24h": 1.0,
      "days_since_snow": 0,
      "melt_alert": false,
      "density_pct": 477.1
    },
    {
      "id": "1085:WA:SNTL",
      "name": "Cayuse Pass",
      "elevation": 5260,
      "swe_in": 22.1,
      "depth_in": 63.0,
      "temp_f": 20.1,
      "swe_change_24h": 0.5,
      "days_since_snow": 0,
      "melt_alert": false,
      "density_pct": 421.0
    },
    {
      "id": "418:WA:SNTL",
      "name": "Corral Pass",
      "elevation": 5810,
      "swe_in": 18.8,
      "depth_in": 53.0,
      "temp_f": 18.1,
      "swe_change_24h": 0.2,
      "days_since_snow": 0,
      "melt_alert": false,
      "density_pct": 425.7
    },
    {
      "id": "375:WA:SNTL",
      "name": "Bumping Ridge",
      "elevation": 4600,
      "swe_in": 11.5,
      "depth_in": 36.0,
      "temp_f": 19.2,
      "swe_change_24h": 0.1,
      "days_since_snow": 0,
      "melt_alert": false,
      "density_pct": 383.3
    },
    {
      "id": "420:WA:SNTL",
      "name": "Cougar Mountain",
      "elevation": 3210,
      "swe_in": 0.3,
      "depth_in": 2.0,
      "temp_f": 27.0,
      "swe_change_24h": 0.3,
      "days_since_snow": 0,
      "melt_alert": false,
      "density_pct": 180.0
    }
  ]
}